{
  "avg": {
    "bytes": 4999.723896663078,
    "sampleInterval": 1
  },
  "dimensions": {
    "date": "2026-06-11"
  },
  "sum": {
    "browserMap": [
      {
        "pageViews": 122,
        "uaBrowserFamily": "Unknown"
      },
      {
        "pageViews": 90,
        "uaBrowserFamily": "Chrome"
      },
      {
        "pageViews": 7,
        "uaBrowserFamily": "Safari"
      },
      {
        "pageViews": 38,
        "uaBrowserFamily": "Firefox"
      },
      {
        "pageViews": 11,
        "uaBrowserFamily": "YandexBot"
      },
      {
        "pageViews": 48,
        "uaBrowserFamily": "MobileSafari"
      },
      {
        "pageViews": 16,
        "uaBrowserFamily": "ChromeMobile"
      },
      {
        "pageViews": 1,
        "uaBrowserFamily": "ChromeMobileWebview"
      },
      {
        "pageViews": 2,
        "uaBrowserFamily": "SamsungInternet"
      },
      {
        "pageViews": 3,
        "uaBrowserFamily": "Edge"
      },
      {
        "pageViews": 1,
        "uaBrowserFamily": "ChromeDerivative"
      },
      {
        "pageViews": 1,
        "uaBrowserFamily": "Brave"
      },
      {
        "pageViews": 367,
        "uaBrowserFamily": "Curl"
      }
    ],
    "bytes": 9289487,
    "countryMap": [
      {
        "bytes": 11156,
        "clientCountryName": "AE",
        "requests": 2
      },
      {
        "bytes": 577038,
        "clientCountryName": "AU",
        "requests": 88
      },
      {
        "bytes": 3167,
        "clientCountryName": "BE",
        "requests": 1
      },
      {
        "bytes": 58494,
        "clientCountryName": "BG",
        "requests": 2
      },
      {
        "bytes": 33744,
        "clientCountryName": "BR",
        "requests": 11
      },
      {
        "bytes": 103119,
        "clientCountryName": "CA",
        "requests": 42
      },
      {
        "bytes": 521,
        "clientCountryName": "CL",
        "requests": 1
      },
      {
        "bytes": 500362,
        "clientCountryName": "CN",
        "requests": 37
      },
      {
        "bytes": 3157,
        "clientCountryName": "CO",
        "requests": 1
      },
      {
        "bytes": 151707,
        "clientCountryName": "CZ",
        "requests": 42
      },
      {
        "bytes": 63887,
        "clientCountryName": "DE",
        "requests": 31
      },
      {
        "bytes": 12570,
        "clientCountryName": "EC",
        "requests": 4
      },
      {
        "bytes": 6629,
        "clientCountryName": "ES",
        "requests": 3
      },
      {
        "bytes": 1535252,
        "clientCountryName": "FR",
        "requests": 420
      },
      {
        "bytes": 58142,
        "clientCountryName": "GB",
        "requests": 22
      },
      {
        "bytes": 15540,
        "clientCountryName": "HK",
        "requests": 5
      },
      {
        "bytes": 8476,
        "clientCountryName": "ID",
        "requests": 2
      },
      {
        "bytes": 13199,
        "clientCountryName": "IE",
        "requests": 5
      },
      {
        "bytes": 1761,
        "clientCountryName": "IL",
        "requests": 1
      },
      {
        "bytes": 93429,
        "clientCountryName": "IN",
        "requests": 5
      },
      {
        "bytes": 6544,
        "clientCountryName": "IQ",
        "requests": 1
      },
      {
        "bytes": 1403192,
        "clientCountryName": "IT",
        "requests": 254
      },
      {
        "bytes": 1181360,
        "clientCountryName": "JP",
        "requests": 74
      },
      {
        "bytes": 3153,
        "clientCountryName": "KE",
        "requests": 1
      },
      {
        "bytes": 8625,
        "clientCountryName": "KH",
        "requests": 6
      },
      {
        "bytes": 295396,
        "clientCountryName": "KR",
        "requests": 46
      },
      {
        "bytes": 6258,
        "clientCountryName": "LB",
        "requests": 1
      },
      {
        "bytes": 39432,
        "clientCountryName": "MA",
        "requests": 11
      },
      {
        "bytes": 3485,
        "clientCountryName": "ML",
        "requests": 1
      },
      {
        "bytes": 1635,
        "clientCountryName": "MX",
        "requests": 2
      },
      {
        "bytes": 613,
        "clientCountryName": "MY",
        "requests": 1
      },
      {
        "bytes": 479061,
        "clientCountryName": "NL",
        "requests": 118
      },
      {
        "bytes": 4049,
        "clientCountryName": "PK",
        "requests": 1
      },
      {
        "bytes": 234125,
        "clientCountryName": "PL",
        "requests": 8
      },
      {
        "bytes": 100142,
        "clientCountryName": "RU",
        "requests": 33
      },
      {
        "bytes": 11393,
        "clientCountryName": "SE",
        "requests": 6
      },
      {
        "bytes": 207798,
        "clientCountryName": "SG",
        "requests": 225
      },
      {
        "bytes": 4761,
        "clientCountryName": "SY",
        "requests": 2
      },
      {
        "bytes": 10699,
        "clientCountryName": "TH",
        "requests": 2
      },
      {
        "bytes": 612,
        "clientCountryName": "UA",
        "requests": 1
      },
      {
        "bytes": 1993809,
        "clientCountryName": "US",
        "requests": 335
      },
      {
        "bytes": 29346,
        "clientCountryName": "UY",
        "requests": 1
      },
      {
        "bytes": 3591,
        "clientCountryName": "VN",
        "requests": 1
      },
      {
        "bytes": 9058,
        "clientCountryName": "ZA",
        "requests": 2
      }
    ],
    "ipClassMap": [
      {
        "ipType": "unknown",
        "requests": 147
      },
      {
        "ipType": "searchEngine",
        "requests": 53
      },
      {
        "ipType": "noRecord",
        "requests": 1658
      }
    ],
    "pageViews": 707,
    "requests": 1858
  },
  "uniq": {
    "uniques": 313
  }
}
