{
  "avg": {
    "bytes": 5855.030129124821,
    "sampleInterval": 1
  },
  "dimensions": {
    "date": "2026-05-13"
  },
  "sum": {
    "browserMap": [
      {
        "pageViews": 331,
        "uaBrowserFamily": "Unknown"
      },
      {
        "pageViews": 92,
        "uaBrowserFamily": "Chrome"
      },
      {
        "pageViews": 6,
        "uaBrowserFamily": "Safari"
      },
      {
        "pageViews": 16,
        "uaBrowserFamily": "Firefox"
      },
      {
        "pageViews": 1,
        "uaBrowserFamily": "BingBot"
      },
      {
        "pageViews": 2,
        "uaBrowserFamily": "GoogleBot"
      },
      {
        "pageViews": 10,
        "uaBrowserFamily": "YandexBot"
      },
      {
        "pageViews": 30,
        "uaBrowserFamily": "MobileSafari"
      },
      {
        "pageViews": 15,
        "uaBrowserFamily": "ChromeMobile"
      },
      {
        "pageViews": 1,
        "uaBrowserFamily": "ChromeMobileWebview"
      },
      {
        "pageViews": 1,
        "uaBrowserFamily": "OperaMobile"
      },
      {
        "pageViews": 1,
        "uaBrowserFamily": "Edge"
      },
      {
        "pageViews": 1,
        "uaBrowserFamily": "Brave"
      }
    ],
    "bytes": 8161912,
    "countryMap": [
      {
        "bytes": 3473,
        "clientCountryName": "AE",
        "requests": 1
      },
      {
        "bytes": 29518,
        "clientCountryName": "AU",
        "requests": 8
      },
      {
        "bytes": 15002,
        "clientCountryName": "BE",
        "requests": 8
      },
      {
        "bytes": 58495,
        "clientCountryName": "BG",
        "requests": 2
      },
      {
        "bytes": 1137846,
        "clientCountryName": "BR",
        "requests": 205
      },
      {
        "bytes": 747177,
        "clientCountryName": "CA",
        "requests": 107
      },
      {
        "bytes": 11790,
        "clientCountryName": "CN",
        "requests": 5
      },
      {
        "bytes": 7450,
        "clientCountryName": "CZ",
        "requests": 3
      },
      {
        "bytes": 50894,
        "clientCountryName": "DE",
        "requests": 25
      },
      {
        "bytes": 25856,
        "clientCountryName": "ES",
        "requests": 8
      },
      {
        "bytes": 63947,
        "clientCountryName": "FI",
        "requests": 13
      },
      {
        "bytes": 201446,
        "clientCountryName": "FR",
        "requests": 49
      },
      {
        "bytes": 22715,
        "clientCountryName": "GB",
        "requests": 7
      },
      {
        "bytes": 21423,
        "clientCountryName": "HK",
        "requests": 6
      },
      {
        "bytes": 6478,
        "clientCountryName": "IE",
        "requests": 3
      },
      {
        "bytes": 6253,
        "clientCountryName": "IL",
        "requests": 1
      },
      {
        "bytes": 98332,
        "clientCountryName": "IN",
        "requests": 6
      },
      {
        "bytes": 12521,
        "clientCountryName": "IQ",
        "requests": 2
      },
      {
        "bytes": 31882,
        "clientCountryName": "JP",
        "requests": 8
      },
      {
        "bytes": 462,
        "clientCountryName": "KH",
        "requests": 1
      },
      {
        "bytes": 3589,
        "clientCountryName": "KZ",
        "requests": 1
      },
      {
        "bytes": 232800,
        "clientCountryName": "LT",
        "requests": 144
      },
      {
        "bytes": 6499,
        "clientCountryName": "LU",
        "requests": 2
      },
      {
        "bytes": 10780,
        "clientCountryName": "MK",
        "requests": 3
      },
      {
        "bytes": 3467,
        "clientCountryName": "MX",
        "requests": 1
      },
      {
        "bytes": 13017,
        "clientCountryName": "NG",
        "requests": 2
      },
      {
        "bytes": 269113,
        "clientCountryName": "NL",
        "requests": 115
      },
      {
        "bytes": 6261,
        "clientCountryName": "PK",
        "requests": 1
      },
      {
        "bytes": 234566,
        "clientCountryName": "PL",
        "requests": 9
      },
      {
        "bytes": 12983,
        "clientCountryName": "PT",
        "requests": 4
      },
      {
        "bytes": 35276,
        "clientCountryName": "RU",
        "requests": 12
      },
      {
        "bytes": 7371,
        "clientCountryName": "SA",
        "requests": 2
      },
      {
        "bytes": 14325,
        "clientCountryName": "SE",
        "requests": 7
      },
      {
        "bytes": 147694,
        "clientCountryName": "SG",
        "requests": 67
      },
      {
        "bytes": 10108,
        "clientCountryName": "TH",
        "requests": 2
      },
      {
        "bytes": 3588,
        "clientCountryName": "TR",
        "requests": 1
      },
      {
        "bytes": 4543326,
        "clientCountryName": "US",
        "requests": 542
      },
      {
        "bytes": 6267,
        "clientCountryName": "VN",
        "requests": 1
      },
      {
        "bytes": 47922,
        "clientCountryName": "T1",
        "requests": 10
      }
    ],
    "ipClassMap": [
      {
        "ipType": "unknown",
        "requests": 317
      },
      {
        "ipType": "searchEngine",
        "requests": 29
      },
      {
        "ipType": "allowlist",
        "requests": 3
      },
      {
        "ipType": "monitoringService",
        "requests": 2
      },
      {
        "ipType": "noRecord",
        "requests": 1033
      },
      {
        "ipType": "tor",
        "requests": 10
      }
    ],
    "pageViews": 507,
    "requests": 1394
  },
  "uniq": {
    "uniques": 288
  }
}
