{
  "avg": {
    "bytes": 3364.7356232514767,
    "sampleInterval": 1
  },
  "dimensions": {
    "date": "2026-04-08"
  },
  "sum": {
    "browserMap": [
      {
        "pageViews": 513,
        "uaBrowserFamily": "Unknown"
      },
      {
        "pageViews": 117,
        "uaBrowserFamily": "Chrome"
      },
      {
        "pageViews": 22,
        "uaBrowserFamily": "Safari"
      },
      {
        "pageViews": 60,
        "uaBrowserFamily": "Firefox"
      },
      {
        "pageViews": 1,
        "uaBrowserFamily": "AppleBot"
      },
      {
        "pageViews": 1,
        "uaBrowserFamily": "BingBot"
      },
      {
        "pageViews": 1,
        "uaBrowserFamily": "GoogleBot"
      },
      {
        "pageViews": 44,
        "uaBrowserFamily": "MobileSafari"
      },
      {
        "pageViews": 17,
        "uaBrowserFamily": "ChromeMobile"
      },
      {
        "pageViews": 1,
        "uaBrowserFamily": "Edge"
      },
      {
        "pageViews": 16,
        "uaBrowserFamily": "ChromeDerivative"
      },
      {
        "pageViews": 1,
        "uaBrowserFamily": "Brave"
      }
    ],
    "bytes": 21648709,
    "countryMap": [
      {
        "bytes": 870982,
        "clientCountryName": "AU",
        "requests": 200
      },
      {
        "bytes": 6263,
        "clientCountryName": "BD",
        "requests": 1
      },
      {
        "bytes": 58495,
        "clientCountryName": "BG",
        "requests": 2
      },
      {
        "bytes": 16927,
        "clientCountryName": "BR",
        "requests": 4
      },
      {
        "bytes": 6259,
        "clientCountryName": "BY",
        "requests": 1
      },
      {
        "bytes": 872889,
        "clientCountryName": "CA",
        "requests": 355
      },
      {
        "bytes": 107001,
        "clientCountryName": "CH",
        "requests": 24
      },
      {
        "bytes": 460467,
        "clientCountryName": "CN",
        "requests": 18
      },
      {
        "bytes": 448195,
        "clientCountryName": "CZ",
        "requests": 19
      },
      {
        "bytes": 30752,
        "clientCountryName": "DE",
        "requests": 51
      },
      {
        "bytes": 631,
        "clientCountryName": "EG",
        "requests": 1
      },
      {
        "bytes": 590428,
        "clientCountryName": "ES",
        "requests": 236
      },
      {
        "bytes": 3619,
        "clientCountryName": "FI",
        "requests": 2
      },
      {
        "bytes": 203811,
        "clientCountryName": "FR",
        "requests": 130
      },
      {
        "bytes": 25754,
        "clientCountryName": "GB",
        "requests": 44
      },
      {
        "bytes": 1136126,
        "clientCountryName": "HK",
        "requests": 175
      },
      {
        "bytes": 1762,
        "clientCountryName": "ID",
        "requests": 1
      },
      {
        "bytes": 818417,
        "clientCountryName": "IE",
        "requests": 320
      },
      {
        "bytes": 753726,
        "clientCountryName": "IN",
        "requests": 102
      },
      {
        "bytes": 399992,
        "clientCountryName": "IT",
        "requests": 157
      },
      {
        "bytes": 219449,
        "clientCountryName": "JP",
        "requests": 118
      },
      {
        "bytes": 511199,
        "clientCountryName": "KR",
        "requests": 78
      },
      {
        "bytes": 6508,
        "clientCountryName": "LT",
        "requests": 1
      },
      {
        "bytes": 1754,
        "clientCountryName": "MY",
        "requests": 1
      },
      {
        "bytes": 5015902,
        "clientCountryName": "NL",
        "requests": 498
      },
      {
        "bytes": 1150359,
        "clientCountryName": "NO",
        "requests": 213
      },
      {
        "bytes": 994,
        "clientCountryName": "NZ",
        "requests": 2
      },
      {
        "bytes": 36536,
        "clientCountryName": "PH",
        "requests": 3
      },
      {
        "bytes": 151531,
        "clientCountryName": "PK",
        "requests": 1
      },
      {
        "bytes": 899127,
        "clientCountryName": "PL",
        "requests": 115
      },
      {
        "bytes": 4636,
        "clientCountryName": "RU",
        "requests": 3
      },
      {
        "bytes": 6547,
        "clientCountryName": "SA",
        "requests": 1
      },
      {
        "bytes": 1029042,
        "clientCountryName": "SE",
        "requests": 194
      },
      {
        "bytes": 1014098,
        "clientCountryName": "SG",
        "requests": 1368
      },
      {
        "bytes": 915,
        "clientCountryName": "SK",
        "requests": 2
      },
      {
        "bytes": 5478,
        "clientCountryName": "TR",
        "requests": 1
      },
      {
        "bytes": 14226,
        "clientCountryName": "TW",
        "requests": 2
      },
      {
        "bytes": 10192,
        "clientCountryName": "UA",
        "requests": 3
      },
      {
        "bytes": 4537876,
        "clientCountryName": "US",
        "requests": 1960
      },
      {
        "bytes": 3467,
        "clientCountryName": "VE",
        "requests": 1
      },
      {
        "bytes": 21985,
        "clientCountryName": "VN",
        "requests": 6
      },
      {
        "bytes": 194392,
        "clientCountryName": "ZA",
        "requests": 20
      }
    ],
    "ipClassMap": [
      {
        "ipType": "unknown",
        "requests": 2294
      },
      {
        "ipType": "searchEngine",
        "requests": 26
      },
      {
        "ipType": "allowlist",
        "requests": 1
      },
      {
        "ipType": "noRecord",
        "requests": 4113
      }
    ],
    "pageViews": 794,
    "requests": 6434
  },
  "uniq": {
    "uniques": 277
  }
}
