{
  "avg": {
    "bytes": 5151.403081090232,
    "sampleInterval": 1
  },
  "dimensions": {
    "date": "2025-08-06"
  },
  "sum": {
    "browserMap": [
      {
        "pageViews": 2483,
        "uaBrowserFamily": "Unknown"
      }
    ],
    "bytes": 30429338,
    "countryMap": [
      {
        "bytes": 1992054,
        "clientCountryName": "AU",
        "requests": 369
      },
      {
        "bytes": 42036,
        "clientCountryName": "BD",
        "requests": 16
      },
      {
        "bytes": 8002,
        "clientCountryName": "BE",
        "requests": 1
      },
      {
        "bytes": 61283,
        "clientCountryName": "BG",
        "requests": 2
      },
      {
        "bytes": 44201,
        "clientCountryName": "BR",
        "requests": 17
      },
      {
        "bytes": 12375,
        "clientCountryName": "CA",
        "requests": 8
      },
      {
        "bytes": 36597,
        "clientCountryName": "CN",
        "requests": 8
      },
      {
        "bytes": 464379,
        "clientCountryName": "CZ",
        "requests": 13
      },
      {
        "bytes": 1065731,
        "clientCountryName": "DE",
        "requests": 135
      },
      {
        "bytes": 7110,
        "clientCountryName": "ES",
        "requests": 2
      },
      {
        "bytes": 2143,
        "clientCountryName": "FI",
        "requests": 1
      },
      {
        "bytes": 73950,
        "clientCountryName": "FR",
        "requests": 50
      },
      {
        "bytes": 61288,
        "clientCountryName": "GB",
        "requests": 2
      },
      {
        "bytes": 9988,
        "clientCountryName": "ID",
        "requests": 6
      },
      {
        "bytes": 11724631,
        "clientCountryName": "IE",
        "requests": 2106
      },
      {
        "bytes": 121030,
        "clientCountryName": "IN",
        "requests": 31
      },
      {
        "bytes": 43978,
        "clientCountryName": "IR",
        "requests": 16
      },
      {
        "bytes": 6507979,
        "clientCountryName": "JP",
        "requests": 1505
      },
      {
        "bytes": 36658,
        "clientCountryName": "KE",
        "requests": 8
      },
      {
        "bytes": 608532,
        "clientCountryName": "KR",
        "requests": 104
      },
      {
        "bytes": 4600,
        "clientCountryName": "KZ",
        "requests": 1
      },
      {
        "bytes": 42455,
        "clientCountryName": "MN",
        "requests": 16
      },
      {
        "bytes": 1370,
        "clientCountryName": "MX",
        "requests": 2
      },
      {
        "bytes": 1684086,
        "clientCountryName": "NL",
        "requests": 312
      },
      {
        "bytes": 298028,
        "clientCountryName": "PL",
        "requests": 18
      },
      {
        "bytes": 35971,
        "clientCountryName": "RO",
        "requests": 9
      },
      {
        "bytes": 184142,
        "clientCountryName": "RU",
        "requests": 30
      },
      {
        "bytes": 198,
        "clientCountryName": "SA",
        "requests": 1
      },
      {
        "bytes": 9198,
        "clientCountryName": "SE",
        "requests": 2
      },
      {
        "bytes": 2807184,
        "clientCountryName": "SG",
        "requests": 898
      },
      {
        "bytes": 211,
        "clientCountryName": "TR",
        "requests": 1
      },
      {
        "bytes": 27142,
        "clientCountryName": "UA",
        "requests": 7
      },
      {
        "bytes": 2365335,
        "clientCountryName": "US",
        "requests": 201
      },
      {
        "bytes": 36831,
        "clientCountryName": "VN",
        "requests": 8
      },
      {
        "bytes": 8642,
        "clientCountryName": "ZA",
        "requests": 1
      }
    ],
    "ipClassMap": [
      {
        "ipType": "unknown",
        "requests": 4910
      },
      {
        "ipType": "searchEngine",
        "requests": 11
      },
      {
        "ipType": "noRecord",
        "requests": 986
      }
    ],
    "pageViews": 2483,
    "requests": 5907
  },
  "uniq": {
    "uniques": 201
  }
}
