{
  "avg": {
    "bytes": 5794.799734098384,
    "sampleInterval": 1
  },
  "dimensions": {
    "date": "2025-06-04"
  },
  "sum": {
    "browserMap": [
      {
        "pageViews": 8262,
        "uaBrowserFamily": "Unknown"
      },
      {
        "pageViews": 7,
        "uaBrowserFamily": "Chrome"
      }
    ],
    "bytes": 82813483,
    "countryMap": [
      {
        "bytes": 32670,
        "clientCountryName": "AE",
        "requests": 10
      },
      {
        "bytes": 4989,
        "clientCountryName": "BE",
        "requests": 2
      },
      {
        "bytes": 139505,
        "clientCountryName": "BG",
        "requests": 26
      },
      {
        "bytes": 23968,
        "clientCountryName": "BR",
        "requests": 5
      },
      {
        "bytes": 18801,
        "clientCountryName": "CA",
        "requests": 5
      },
      {
        "bytes": 674700,
        "clientCountryName": "CN",
        "requests": 191
      },
      {
        "bytes": 2455945,
        "clientCountryName": "DE",
        "requests": 55
      },
      {
        "bytes": 36234,
        "clientCountryName": "EC",
        "requests": 8
      },
      {
        "bytes": 2086,
        "clientCountryName": "FI",
        "requests": 1
      },
      {
        "bytes": 34907,
        "clientCountryName": "FR",
        "requests": 8
      },
      {
        "bytes": 148118,
        "clientCountryName": "GB",
        "requests": 33
      },
      {
        "bytes": 2083,
        "clientCountryName": "HK",
        "requests": 1
      },
      {
        "bytes": 12952,
        "clientCountryName": "ID",
        "requests": 2
      },
      {
        "bytes": 74541865,
        "clientCountryName": "IE",
        "requests": 13236
      },
      {
        "bytes": 30592,
        "clientCountryName": "IL",
        "requests": 1
      },
      {
        "bytes": 313925,
        "clientCountryName": "IN",
        "requests": 50
      },
      {
        "bytes": 7888,
        "clientCountryName": "IT",
        "requests": 1
      },
      {
        "bytes": 16286,
        "clientCountryName": "JP",
        "requests": 4
      },
      {
        "bytes": 36250,
        "clientCountryName": "KE",
        "requests": 8
      },
      {
        "bytes": 5474,
        "clientCountryName": "KR",
        "requests": 2
      },
      {
        "bytes": 67674,
        "clientCountryName": "NC",
        "requests": 16
      },
      {
        "bytes": 67480,
        "clientCountryName": "NG",
        "requests": 16
      },
      {
        "bytes": 1351663,
        "clientCountryName": "NL",
        "requests": 219
      },
      {
        "bytes": 152938,
        "clientCountryName": "PL",
        "requests": 5
      },
      {
        "bytes": 184700,
        "clientCountryName": "RU",
        "requests": 29
      },
      {
        "bytes": 7897,
        "clientCountryName": "SC",
        "requests": 1
      },
      {
        "bytes": 421474,
        "clientCountryName": "SG",
        "requests": 68
      },
      {
        "bytes": 36128,
        "clientCountryName": "TH",
        "requests": 8
      },
      {
        "bytes": 7898,
        "clientCountryName": "UA",
        "requests": 1
      },
      {
        "bytes": 1908753,
        "clientCountryName": "US",
        "requests": 263
      },
      {
        "bytes": 67640,
        "clientCountryName": "ZA",
        "requests": 16
      }
    ],
    "ipClassMap": [
      {
        "ipType": "unknown",
        "requests": 8609
      },
      {
        "ipType": "searchEngine",
        "requests": 2
      },
      {
        "ipType": "noRecord",
        "requests": 5680
      }
    ],
    "pageViews": 8269,
    "requests": 14291
  },
  "uniq": {
    "uniques": 216
  }
}
