{
  "avg": {
    "bytes": 4304.146356399265,
    "sampleInterval": 1
  },
  "dimensions": {
    "date": "2024-10-11"
  },
  "sum": {
    "browserMap": [
      {
        "pageViews": 1483,
        "uaBrowserFamily": "Unknown"
      },
      {
        "pageViews": 91,
        "uaBrowserFamily": "Chrome"
      },
      {
        "pageViews": 2,
        "uaBrowserFamily": "Firefox"
      },
      {
        "pageViews": 1,
        "uaBrowserFamily": "TwitterBot"
      },
      {
        "pageViews": 3,
        "uaBrowserFamily": "YandexBot"
      },
      {
        "pageViews": 9,
        "uaBrowserFamily": "MobileSafari"
      },
      {
        "pageViews": 1,
        "uaBrowserFamily": "ChromeMobile"
      },
      {
        "pageViews": 3,
        "uaBrowserFamily": "Edge"
      },
      {
        "pageViews": 1,
        "uaBrowserFamily": "ChromeHeadless"
      }
    ],
    "bytes": 14057342,
    "countryMap": [
      {
        "bytes": 104508,
        "clientCountryName": "AU",
        "requests": 110
      },
      {
        "bytes": 109548,
        "clientCountryName": "BG",
        "requests": 27
      },
      {
        "bytes": 190548,
        "clientCountryName": "BR",
        "requests": 24
      },
      {
        "bytes": 28981,
        "clientCountryName": "CA",
        "requests": 12
      },
      {
        "bytes": 724898,
        "clientCountryName": "CH",
        "requests": 769
      },
      {
        "bytes": 79048,
        "clientCountryName": "CN",
        "requests": 19
      },
      {
        "bytes": 117928,
        "clientCountryName": "CZ",
        "requests": 27
      },
      {
        "bytes": 195142,
        "clientCountryName": "DE",
        "requests": 22
      },
      {
        "bytes": 7041,
        "clientCountryName": "FR",
        "requests": 3
      },
      {
        "bytes": 91898,
        "clientCountryName": "GB",
        "requests": 35
      },
      {
        "bytes": 6655,
        "clientCountryName": "HK",
        "requests": 1
      },
      {
        "bytes": 8262342,
        "clientCountryName": "IE",
        "requests": 1729
      },
      {
        "bytes": 1879,
        "clientCountryName": "KR",
        "requests": 2
      },
      {
        "bytes": 3298,
        "clientCountryName": "MD",
        "requests": 1
      },
      {
        "bytes": 8937,
        "clientCountryName": "NL",
        "requests": 5
      },
      {
        "bytes": 31245,
        "clientCountryName": "PL",
        "requests": 3
      },
      {
        "bytes": 44122,
        "clientCountryName": "PY",
        "requests": 6
      },
      {
        "bytes": 24928,
        "clientCountryName": "RO",
        "requests": 8
      },
      {
        "bytes": 1649912,
        "clientCountryName": "RU",
        "requests": 54
      },
      {
        "bytes": 253286,
        "clientCountryName": "SG",
        "requests": 51
      },
      {
        "bytes": 10312,
        "clientCountryName": "TH",
        "requests": 4
      },
      {
        "bytes": 10874,
        "clientCountryName": "TW",
        "requests": 4
      },
      {
        "bytes": 8285,
        "clientCountryName": "UA",
        "requests": 3
      },
      {
        "bytes": 2091727,
        "clientCountryName": "US",
        "requests": 347
      }
    ],
    "ipClassMap": [
      {
        "ipType": "unknown",
        "requests": 90
      },
      {
        "ipType": "searchEngine",
        "requests": 19
      },
      {
        "ipType": "noRecord",
        "requests": 3157
      }
    ],
    "pageViews": 1594,
    "requests": 3266
  },
  "uniq": {
    "uniques": 150
  }
}
