{
  "avg": {
    "bytes": 2402.577334809893,
    "sampleInterval": 1
  },
  "dimensions": {
    "date": "2026-04-15"
  },
  "sum": {
    "browserMap": [
      {
        "pageViews": 717,
        "uaBrowserFamily": "Unknown"
      },
      {
        "pageViews": 54,
        "uaBrowserFamily": "Chrome"
      },
      {
        "pageViews": 3,
        "uaBrowserFamily": "Safari"
      },
      {
        "pageViews": 16,
        "uaBrowserFamily": "Firefox"
      },
      {
        "pageViews": 1,
        "uaBrowserFamily": "AppleBot"
      },
      {
        "pageViews": 2,
        "uaBrowserFamily": "GoogleBot"
      },
      {
        "pageViews": 23,
        "uaBrowserFamily": "MobileSafari"
      },
      {
        "pageViews": 27,
        "uaBrowserFamily": "ChromeMobile"
      },
      {
        "pageViews": 2,
        "uaBrowserFamily": "SamsungInternet"
      },
      {
        "pageViews": 2,
        "uaBrowserFamily": "ChromeDerivative"
      },
      {
        "pageViews": 1,
        "uaBrowserFamily": "Brave"
      }
    ],
    "bytes": 13017164,
    "countryMap": [
      {
        "bytes": 612820,
        "clientCountryName": "AU",
        "requests": 95
      },
      {
        "bytes": 58498,
        "clientCountryName": "BG",
        "requests": 2
      },
      {
        "bytes": 54701,
        "clientCountryName": "BR",
        "requests": 17
      },
      {
        "bytes": 1637123,
        "clientCountryName": "CA",
        "requests": 237
      },
      {
        "bytes": 122503,
        "clientCountryName": "CN",
        "requests": 29
      },
      {
        "bytes": 3591,
        "clientCountryName": "CO",
        "requests": 1
      },
      {
        "bytes": 472885,
        "clientCountryName": "CZ",
        "requests": 32
      },
      {
        "bytes": 36128,
        "clientCountryName": "DE",
        "requests": 14
      },
      {
        "bytes": 6258,
        "clientCountryName": "DZ",
        "requests": 1
      },
      {
        "bytes": 27318,
        "clientCountryName": "ES",
        "requests": 8
      },
      {
        "bytes": 6253,
        "clientCountryName": "ET",
        "requests": 1
      },
      {
        "bytes": 2284500,
        "clientCountryName": "FR",
        "requests": 831
      },
      {
        "bytes": 73088,
        "clientCountryName": "GB",
        "requests": 28
      },
      {
        "bytes": 3605,
        "clientCountryName": "GR",
        "requests": 1
      },
      {
        "bytes": 597118,
        "clientCountryName": "HK",
        "requests": 92
      },
      {
        "bytes": 28804,
        "clientCountryName": "ID",
        "requests": 12
      },
      {
        "bytes": 9322,
        "clientCountryName": "IE",
        "requests": 4
      },
      {
        "bytes": 153910,
        "clientCountryName": "IN",
        "requests": 52
      },
      {
        "bytes": 32948,
        "clientCountryName": "IQ",
        "requests": 2
      },
      {
        "bytes": 299191,
        "clientCountryName": "IT",
        "requests": 47
      },
      {
        "bytes": 706918,
        "clientCountryName": "JP",
        "requests": 330
      },
      {
        "bytes": 6255,
        "clientCountryName": "KE",
        "requests": 1
      },
      {
        "bytes": 48072,
        "clientCountryName": "KR",
        "requests": 88
      },
      {
        "bytes": 6266,
        "clientCountryName": "LB",
        "requests": 1
      },
      {
        "bytes": 10940,
        "clientCountryName": "LT",
        "requests": 7
      },
      {
        "bytes": 26447,
        "clientCountryName": "MX",
        "requests": 5
      },
      {
        "bytes": 525317,
        "clientCountryName": "NL",
        "requests": 113
      },
      {
        "bytes": 333913,
        "clientCountryName": "NO",
        "requests": 135
      },
      {
        "bytes": 6266,
        "clientCountryName": "PE",
        "requests": 1
      },
      {
        "bytes": 4436,
        "clientCountryName": "PH",
        "requests": 2
      },
      {
        "bytes": 237273,
        "clientCountryName": "PL",
        "requests": 9
      },
      {
        "bytes": 35714,
        "clientCountryName": "PT",
        "requests": 11
      },
      {
        "bytes": 10875,
        "clientCountryName": "RU",
        "requests": 3
      },
      {
        "bytes": 6404,
        "clientCountryName": "SE",
        "requests": 2
      },
      {
        "bytes": 172235,
        "clientCountryName": "SG",
        "requests": 136
      },
      {
        "bytes": 5472,
        "clientCountryName": "TN",
        "requests": 1
      },
      {
        "bytes": 11064,
        "clientCountryName": "TR",
        "requests": 3
      },
      {
        "bytes": 4228593,
        "clientCountryName": "US",
        "requests": 3039
      },
      {
        "bytes": 11916,
        "clientCountryName": "VN",
        "requests": 3
      },
      {
        "bytes": 3152,
        "clientCountryName": "ZA",
        "requests": 1
      },
      {
        "bytes": 99072,
        "clientCountryName": "T1",
        "requests": 21
      }
    ],
    "ipClassMap": [
      {
        "ipType": "unknown",
        "requests": 2661
      },
      {
        "ipType": "searchEngine",
        "requests": 21
      },
      {
        "ipType": "monitoringService",
        "requests": 4
      },
      {
        "ipType": "noRecord",
        "requests": 2711
      },
      {
        "ipType": "tor",
        "requests": 21
      }
    ],
    "pageViews": 848,
    "requests": 5418
  },
  "uniq": {
    "uniques": 321
  }
}
