{
  "avg": {
    "bytes": 2546.2201756264726,
    "sampleInterval": 1
  },
  "dimensions": {
    "date": "2025-05-05"
  },
  "sum": {
    "browserMap": [
      {
        "pageViews": 52,
        "uaBrowserFamily": "Unknown"
      },
      {
        "pageViews": 200,
        "uaBrowserFamily": "Chrome"
      },
      {
        "pageViews": 4,
        "uaBrowserFamily": "Safari"
      },
      {
        "pageViews": 8,
        "uaBrowserFamily": "Firefox"
      },
      {
        "pageViews": 2,
        "uaBrowserFamily": "AppleBot"
      },
      {
        "pageViews": 4,
        "uaBrowserFamily": "GoogleBot"
      },
      {
        "pageViews": 27,
        "uaBrowserFamily": "MobileSafari"
      },
      {
        "pageViews": 4,
        "uaBrowserFamily": "Edge"
      },
      {
        "pageViews": 1,
        "uaBrowserFamily": "ChromeDerivative"
      }
    ],
    "bytes": 11888302,
    "countryMap": [
      {
        "bytes": 66549,
        "clientCountryName": "AL",
        "requests": 16
      },
      {
        "bytes": 109088,
        "clientCountryName": "BD",
        "requests": 25
      },
      {
        "bytes": 225540,
        "clientCountryName": "BG",
        "requests": 53
      },
      {
        "bytes": 4434,
        "clientCountryName": "BR",
        "requests": 1
      },
      {
        "bytes": 14827,
        "clientCountryName": "CA",
        "requests": 4
      },
      {
        "bytes": 15532,
        "clientCountryName": "CH",
        "requests": 4
      },
      {
        "bytes": 69113,
        "clientCountryName": "CN",
        "requests": 15
      },
      {
        "bytes": 486650,
        "clientCountryName": "CZ",
        "requests": 18
      },
      {
        "bytes": 2160883,
        "clientCountryName": "DE",
        "requests": 1953
      },
      {
        "bytes": 5473,
        "clientCountryName": "FI",
        "requests": 2
      },
      {
        "bytes": 29525,
        "clientCountryName": "FR",
        "requests": 9
      },
      {
        "bytes": 1516709,
        "clientCountryName": "GB",
        "requests": 23
      },
      {
        "bytes": 43470,
        "clientCountryName": "HK",
        "requests": 11
      },
      {
        "bytes": 103096,
        "clientCountryName": "IN",
        "requests": 5
      },
      {
        "bytes": 2325,
        "clientCountryName": "IT",
        "requests": 1
      },
      {
        "bytes": 1443185,
        "clientCountryName": "JP",
        "requests": 18
      },
      {
        "bytes": 4403,
        "clientCountryName": "KR",
        "requests": 1
      },
      {
        "bytes": 957682,
        "clientCountryName": "NL",
        "requests": 164
      },
      {
        "bytes": 66531,
        "clientCountryName": "NP",
        "requests": 16
      },
      {
        "bytes": 30530,
        "clientCountryName": "PL",
        "requests": 1
      },
      {
        "bytes": 7775,
        "clientCountryName": "RU",
        "requests": 1
      },
      {
        "bytes": 506711,
        "clientCountryName": "SC",
        "requests": 133
      },
      {
        "bytes": 176176,
        "clientCountryName": "SG",
        "requests": 40
      },
      {
        "bytes": 3830457,
        "clientCountryName": "US",
        "requests": 2153
      },
      {
        "bytes": 11638,
        "clientCountryName": "XX",
        "requests": 2
      }
    ],
    "ipClassMap": [
      {
        "ipType": "unknown",
        "requests": 3983
      },
      {
        "ipType": "searchEngine",
        "requests": 23
      },
      {
        "ipType": "noRecord",
        "requests": 663
      }
    ],
    "pageViews": 302,
    "requests": 4669
  },
  "uniq": {
    "uniques": 177
  }
}
